{
  "cli": {
    "version": ">= 10.2.4"
  },
  "build": {
    "development": {
      "developmentClient": true,
      "distribution": "internal",
      "env": {
        "EXPO_PUBLIC_API_URL": "https://carpool-backend-beryl.vercel.app"
      },
      "channel": "development"
    },
    "preview": {
      "distribution": "internal",
      "channel": "preview"
    },
    "production": {
      "env": {
        "EXPO_PUBLIC_API_URL": "https://carpool-backend-beryl.vercel.app"
      },
      "channel": "production"
    }
  },
  "submit": {
    "production": {
      "ios": {
        "appleId": "jdsantelicesl@icloud.com",
        "ascAppId": "6657955090",
        "appleTeamId": "B3A9TZB6G3"
      }
    }
  }
}
